auto_commit_ai/__init__.py
auto_commit_ai/_version.py
auto_commit_ai/cli.py
auto_commit_ai/config.py
auto_commit_ai/core.py
auto_commit_ai/git_utils.py
auto_commit_ai/providers/__init__.py
auto_commit_ai/providers/azure.py
auto_commit_ai/providers/base.py
auto_commit_ai/providers/factory.py
auto_commit_ai/providers/google.py
auto_commit_ai/providers/ollama.py
auto_commit_ai/providers/openai.py
auto_commit_ai/providers/prompts.py
auto_commit_ai-0.3.2.dist-info/licenses/LICENSE
auto_commit_ai-0.3.2.dist-info/METADATA
auto_commit_ai-0.3.2.dist-info/WHEEL
auto_commit_ai-0.3.2.dist-info/entry_points.txt
auto_commit_ai-0.3.2.dist-info/top_level.txt
auto_commit_ai-0.3.2.dist-info/RECORD
