Metadata-Version: 2.4
Name: auto-commit-ai
Version: 0.3.2
Summary: Generate automatic commit messages using AI
Author-email: Toni Miquel Llull <tonimiquel.llull@gmail.com>
License: MIT License
Project-URL: Homepage, https://github.com/tmllull/auto-commit-ai
Project-URL: Repository, https://github.com/tmllull/auto-commit-ai
Project-URL: Issues, https://github.com/tmllull/auto-commit-ai/issues
Classifier: Development Status :: 4 - Beta
Classifier: Intended Audience :: Developers
Classifier: License :: OSI Approved :: MIT License
Classifier: Operating System :: OS Independent
Classifier: Programming Language :: Python :: 3
Classifier: Programming Language :: Python :: 3.10
Classifier: Programming Language :: Python :: 3.11
Classifier: Programming Language :: Python :: 3.12
Classifier: Programming Language :: Python :: 3.13
Requires-Python: >=3.10
License-File: LICENSE
Requires-Dist: python-dotenv
Requires-Dist: openai
Requires-Dist: google-genai
Requires-Dist: GitPython
Requires-Dist: ollama
Dynamic: license-file
